fastapi_cognito_security/__init__.py
fastapi_cognito_security-0.0.2.dist-info/LICENSE
fastapi_cognito_security-0.0.2.dist-info/METADATA
fastapi_cognito_security-0.0.2.dist-info/WHEEL
fastapi_cognito_security-0.0.2.dist-info/top_level.txt
fastapi_cognito_security-0.0.2.dist-info/RECORD
