Metadata-Version: 2.1
Name: fastapi-cognito-security
Version: 0.0.2
Summary: A FastAPI Security object for AWS Cognito - supports both access and id tokens
Home-page: https://github.com/QuiNovas/fastapi-cognito-security
Author: QuiNovas
Author-email: pypi@quinovas.com
License: Apache 2.0
Keywords: fastapi,cognito
Classifier: Development Status :: 4 - Beta
Classifier: Intended Audience :: Developers
Classifier: License :: OSI Approved :: Apache Software License
Classifier: Programming Language :: Python :: 3.9
Requires-Python: >=3.9
License-File: LICENSE
Requires-Dist: cognitojwt[async]
Requires-Dist: fastapi
